{
  "Sprite": 195,
  "sprite_label": "present",
  "map_location_label": "Lilliput Steps_Rooms_Main-Room",
  "Type": "item",
  "flag_condition": null,
  "d1_pointer": "C7D84F",
  "d1_flags": [
    "1. goto C7D9EC if 226 is set",
    "1. goto C7D9FD if 226 is set",
    "1. goto C7DA0C if 227 is set",
    "1. goto C7DA33 if 227 is set",
    "1. goto C7DA58 if 228 is set",
    "1. goto C7DA7C if 228 is set",
    "1. goto C7DA8F if 229 is set",
    "1. goto C7DAB6 if 229 is set",
    "3. set 226",
    "4. clear 226"
  ],
  "d1_addresses": [
    "C7D84F",
    "C7D87F",
    "C7D8D9",
    "C7D8E6",
    "C7D8EE",
    "C7D907",
    "C7D90D",
    "C7D92A",
    "C7D947",
    "C7D958",
    "C7D967",
    "C7D991",
    "C7D9CF",
    "C7D9EC",
    "C7D9FD",
    "C7DA0C",
    "C7DA33",
    "C7DA58",
    "C7DA7C",
    "C7DA8F",
    "C7DAB6",
    "C7DC85",
    "C7E5F3",
    "C7E5FE"
  ],
  "d1_text": "L_C7D84F:\r\n[SET_FLAG 226]\r\n[GOSUB L_C7D87F]\r\n[CLR_FLAG 226]\r\n[END]",
  "d1_lines": [
    "L_C7D84F:",
    "[SET_FLAG 226]",
    "[GOSUB L_C7D87F]",
    "[CLR_FLAG 226]",
    "[END]"
  ],
  "d1_unrolled": {
    "[SET_FLAG 226]": null,
    "[GOSUB L_C7D87F]:C7D87F": {
      "[BACKUP_REGS_LOCAL]": null,
      "[CHECK_INTERACTED_PRESENT_OPENED]": null,
      "[BACKUP_REGS_GLOBAL]": null,
      "[GET_PARTY_MEMBER 1][SWAP_ARG_RESULT]": null,
      "[GOSUB L_C7D90D]:C7D90D": {
        "[GOTO_IF_FLAG 226 L_C7D9EC]:C7D9EC": {
          "\u00ef\u00bf\u00bd[PRINT_NAME REG_ARGUMENT] opened the present.[END]": null
        },
        "[GOTO_IF_FLAG 227 L_C7DA0C]:C7DA0C": {
          "\u00ef\u00bf\u00bd[PRINT_NAME REG_ARGUMENT] dug around in the trash can.[END]": null
        },
        "[GOTO_IF_FLAG 228 L_C7DA58]:C7DA58": {
          "\u00ef\u00bf\u00bd[PRINT_NAME REG_ARGUMENT] opened the chest.[END]": null
        },
        "[GOTO_IF_FLAG 229 L_C7DA8F]:C7DA8F": {
          "\u00ef\u00bf\u00bd[PRINT_NAME REG_ARGUMENT] opened the casket.[END]": null
        },
        "[END]": null
      },
      "[PLAY_SFX 16]": null,
      "[OPEN_INTERACTED_PRESENT]": null,
      "[WAIT][LINE_BREAK]": null,
      "[RESTORE_REGS_GLOBAL]": null,
      "[GOTO_IF_TRUE L_C7D907]:C7D907": {
        "[GOSUB L_C7D9CF]:C7D9CF": {
          "[GOTO_IF_FLAG 226 L_C7D9FD]:C7D9FD": {
            "[START_LINE]": null,
            "\u00ef\u00bf\u00bdBut it was empty.[HALT][END]": null
          },
          "[GOTO_IF_FLAG 227 L_C7DA33]:C7DA33": {
            "[START_LINE]": null,
            "\u00ef\u00bf\u00bdThere was just plain ol' garbage in the trash can.[HALT][END]": null
          },
          "[GOTO_IF_FLAG 228 L_C7DA7C]:C7DA7C": {
            "[START_LINE]": null,
            "\u00ef\u00bf\u00bdBut the chest was empty.[HALT][END]": null
          },
          "[GOTO_IF_FLAG 229 L_C7DAB6]:C7DAB6": {
            "[START_LINE]": null,
            "\u00ef\u00bf\u00bdBut the casket was empty.[HALT][END]": null
          },
          "[END]": null
        },
        "[END]": null
      },
      "[GOSUB L_C7D92A]:C7D92A": "Present Case/Switch - Has Contents",
      "[RESTORE_REGS_LOCAL]": null,
      "[GOTO_IF_FALSE L_C7D8EE]:C7D8EE": "Present Case/Switch - No Contents",
      "[SWAP_ARG_RESULT]": null,
      "[GOSUB L_C7D947]:C7D947": {
        "[START_LINE]": null,
        "\u00ef\u00bf\u00bdThere is a [PRINT_ITEM REG_ARGUMENT] inside![WAIT][END]": null
      },
      "[INV_HAS_SPACE ANY][GOTO_IF_FALSE L_C7D8E6]:C7D8E6": {
        "[GOSUB L_C7D991]:C7D991": {
          "[START_LINE]": null,
          "[GET_PARTY_MEMBER 1]\u00ef\u00bf\u00bdBut, [GOSUB L_C7E5F3]:C7E5F3": {
            "[CHECK_EQUAL 2][GOTO_IF_TRUE L_C7E5FE]:C7E5FE": {
              "she[END]": null
            },
            "he[END]": null
          },
          " has got too much stuff already.[HALT][END]": null
        },
        "[CLOSE_INTERACTED_PRESENT]": null,
        "[END]": null
      },
      "[GOSUB L_C7DC85]:C7DC85": "Function - Check KO/Diamondized Status",
      "[GOTO_IF_TRUE L_C7D8D9]:C7D8D9": {
        "[GOSUB L_C7D967]:C7D967": "Loop - Add Item to Other's Stuff",
        "[GIVE_ITEM_RETURN_SLOT REG_RESULT REG_ARGUMENT]": null,
        "[PLAY_SFX 116]": null,
        "[END]": null
      },
      "[GOSUB L_C7D958]:C7D958": {
        "[START_LINE]": null,
        "\u00ef\u00bf\u00bd[PRINT_NAME REG_ARGUMENT] takes it.[SWAP_ARG_RESULT]": null,
        "[HALT][END]": null
      },
      "[GIVE_ITEM_RETURN_SLOT REG_RESULT REG_ARGUMENT]": null,
      "[PLAY_SFX 116]": null,
      "[END]": null
    },
    "[CLR_FLAG 226]": null,
    "[END]": null
  },
  "d2_pointer": null,
  "d2_flags": [],
  "d2_addresses": [],
  "d2_text": null,
  "d2_lines": null,
  "d2_unrolled": {},
  "x_pixel_abs": 3160,
  "y_pixel_abs": 1968,
  "x_tile": 98,
  "y_tile": 61,
  "x_sector": 12,
  "y_sector": 7,
  "x_sector_offset": 88,
  "y_sector_offset": 176,
  "Event Flag": 821,
  "flag_label": "Unknown Flag",
  "Show Sprite": "always",
  "Direction": "down",
  "Movement": 9,
  "Text Pointer 1": "data_32.l_0xc7d84f",
  "Text Pointer 2": "$37"
}